_yaml.cp38-win_amd64.pyd
yaml/__init__.py
yaml/composer.py
yaml/constructor.py
yaml/cyaml.py
yaml/dumper.py
yaml/emitter.py
yaml/error.py
yaml/events.py
yaml/loader.py
yaml/nodes.py
yaml/parser.py
yaml/reader.py
yaml/representer.py
yaml/resolver.py
yaml/scanner.py
yaml/serializer.py
yaml/tokens.py
yaml/__pycache__/__init__.cpython-38.pyc
yaml/__pycache__/composer.cpython-38.pyc
yaml/__pycache__/constructor.cpython-38.pyc
yaml/__pycache__/cyaml.cpython-38.pyc
yaml/__pycache__/dumper.cpython-38.pyc
yaml/__pycache__/emitter.cpython-38.pyc
yaml/__pycache__/error.cpython-38.pyc
yaml/__pycache__/events.cpython-38.pyc
yaml/__pycache__/loader.cpython-38.pyc
yaml/__pycache__/nodes.cpython-38.pyc
yaml/__pycache__/parser.cpython-38.pyc
yaml/__pycache__/reader.cpython-38.pyc
yaml/__pycache__/representer.cpython-38.pyc
yaml/__pycache__/resolver.cpython-38.pyc
yaml/__pycache__/scanner.cpython-38.pyc
yaml/__pycache__/serializer.cpython-38.pyc
yaml/__pycache__/tokens.cpython-38.pyc
PyYAML-5.3.1.dist-info/LICENSE
PyYAML-5.3.1.dist-info/METADATA
PyYAML-5.3.1.dist-info/WHEEL
PyYAML-5.3.1.dist-info/RECORD
